aitta_client/__init__.py
aitta_client/authentication.py
aitta_client/client.py
aitta_client/wrappers.py
aitta_client/api/__init__.py
aitta_client/api/data_structures.py
aitta_client/api/errors.py
aitta_client/api/wrappers.py
aitta_client-0.3.2.dist-info/METADATA
aitta_client-0.3.2.dist-info/WHEEL
aitta_client-0.3.2.dist-info/top_level.txt
aitta_client-0.3.2.dist-info/RECORD
