Metadata-Version: 2.4
Name: aitta_client
Version: 0.3.2
Summary: Python client for Aitta HPC ML inference platform
Author: CSC - IT Center for Science Oy
License: MIT License
Classifier: Programming Language :: Python :: 3
Classifier: Operating System :: OS Independent
Classifier: License :: OSI Approved :: MIT License
Requires-Python: >=3.11
Requires-Dist: requests~=2.28
Requires-Dist: pydantic~=2.5
Requires-Dist: PyJWT~=2.8
Provides-Extra: test
Requires-Dist: pytest; extra == "test"
Provides-Extra: examples
Requires-Dist: openai; extra == "examples"
